music/__init__.py
music/tables.py
music/utils.py
music/core/__init__.py
music/core/functions.py
music/core/io.py
music/core/filters/__init__.py
music/core/filters/adsr.py
music/core/filters/fade.py
music/core/filters/impulse_response.py
music/core/filters/localization.py
music/core/filters/loud.py
music/core/filters/reverb.py
music/core/filters/stretches.py
music/core/synths/__init__.py
music/core/synths/envelopes.py
music/core/synths/noises.py
music/core/synths/notes.py
music/legacy/CanonicalSynth.py
music/legacy/IteratorSynth.py
music/legacy/__init__.py
music/legacy/classes.py
music/legacy/tables.py
music/legacy/pieces/__init__.py
music/legacy/pieces/testSong2.py
music/singing/__init__.py
music/singing/bootstrap.py
music/singing/perform.py
music/structures/__init__.py
music/structures/permutations.py
music/structures/symmetry.py
music/structures/peals/__init__.py
music/structures/peals/base.py
music/structures/peals/peals.py
music/structures/peals/plain_changes.py
music-1.0.0b5.dist-info/LICENSE
music-1.0.0b5.dist-info/METADATA
music-1.0.0b5.dist-info/WHEEL
music-1.0.0b5.dist-info/top_level.txt
music-1.0.0b5.dist-info/RECORD
