Metadata-Version: 2.1
Name: music
Version: 1.0.0b5
Summary: Extreme-fidelity synthesis of musical elements, based on the MASS framework
Author-email: Renato Fabbri <renato.fabbri@gmail.com>, Jacopo Donati <jacopo.donati@gmail.com>
License: MIT License
Project-URL: Homepage, https://github.com/ttm/music
Project-URL: Issues, https://github.com/ttm/music/issues
Keywords: acoustics,AM,art,audio,campanology,change ringing,filter,FM,HRTF,LUT,MASS,multimedia,music,noise,PCM,permutation,physics,psychophysics,signal processing,sing,sound,spatialization,speech,synth
Classifier: Programming Language :: Python :: 3
Classifier: License :: OSI Approved :: MIT License
Classifier: Operating System :: OS Independent
Classifier: Development Status :: 5 - Production/Stable
Classifier: Intended Audience :: Science/Research
Classifier: Intended Audience :: Healthcare Industry
Classifier: Intended Audience :: Telecommunications Industry
Classifier: Intended Audience :: Developers
Classifier: Intended Audience :: Education
Classifier: Intended Audience :: Religion
Classifier: Topic :: Scientific/Engineering :: Physics
Classifier: Topic :: Scientific/Engineering :: Visualization
Classifier: Topic :: Scientific/Engineering :: Information Analysis
Classifier: Topic :: Multimedia :: Sound/Audio :: Sound Synthesis
Classifier: Topic :: Multimedia :: Sound/Audio :: Editors
Classifier: Topic :: Multimedia :: Sound/Audio :: Mixers
Classifier: Topic :: Multimedia :: Sound/Audio :: Speech
Classifier: Topic :: Multimedia :: Sound/Audio :: Sound Synthesis
Classifier: Topic :: Artistic Software
Requires-Python: >=3.0
License-File: LICENSE
Requires-Dist: colorama >=0.4.6
Requires-Dist: matplotlib >=3.7.1
Requires-Dist: numpy >=1.26.4
Requires-Dist: scipy >=1.12.0
Requires-Dist: sympy >=1.12
Requires-Dist: termcolor >=2.4.0
